kollocate/__init__.py
kollocate/analyze.py
kollocate/index.py
kollocate/search.py
kollocate/indexdir/MAIN_vxol2ststxvi5mkc.seg
kollocate/indexdir/_MAIN_1.toc
kollocate-0.0.2.dist-info/LICENSE
kollocate-0.0.2.dist-info/METADATA
kollocate-0.0.2.dist-info/WHEEL
kollocate-0.0.2.dist-info/top_level.txt
kollocate-0.0.2.dist-info/RECORD
